{"month":3,"year":2026,"stats":{"hasWallpaper":3,"coverage":"9.7%","total":31},"yearMonth":"2026-03","wallpapers":{"01":{"date":"2026-03-01","copyright":"Cachoeira Olo’upena, ilha de Molokai, Havaí, Estados Unidos","previewUrl":"https://cn.bing.com/th?id=OHR.OloupenaFalls_PT-BR4023643923_UHD.jpg","dateUrl":"day/202603/01.html","downloadUrl":"https://cn.bing.com/th?id=OHR.OloupenaFalls_PT-BR4023643923_UHD.jpg","title":"Cachoeira Olo’upena, ilha de Molokai, Havaí, Estados Unidos","desc":"Cachoeira Olo’upena, ilha de Molokai, Havaí, Estados Unidos"},"02":{"date":"2026-03-02","copyright":"Bondinho e Pão de Açúcar no Rio de Janeiro","previewUrl":"https://cn.bing.com/th?id=OHR.AnivRio_PT-BR3855636507_UHD.jpg","dateUrl":"day/202603/02.html","downloadUrl":"https://cn.bing.com/th?id=OHR.AnivRio_PT-BR3855636507_UHD.jpg","title":"Bondinho e Pão de Açúcar no Rio de Janeiro","desc":"Bondinho e Pão de Açúcar no Rio de Janeiro"},"03":{"date":"2026-03-03","copyright":"Porto e barcos de cauda longa em Ko Samui, Tailândia","previewUrl":"https://cn.bing.com/th?id=OHR.SamuiThailand_PT-BR3822247577_UHD.jpg","dateUrl":"day/202603/03.html","downloadUrl":"https://cn.bing.com/th?id=OHR.SamuiThailand_PT-BR3822247577_UHD.jpg","title":"Porto e barcos de cauda longa em Ko Samui, Tailândia","desc":"Porto e barcos de cauda longa em Ko Samui, Tailândia"}}}