{"month":6,"year":2026,"stats":{"hasWallpaper":26,"coverage":"86.7%","total":30},"yearMonth":"2026-06","wallpapers":{"22":{"date":"2026-06-22","copyright":"富士山","previewUrl":"https://cn.bing.com/th?id=OHR.Fujisan_JA-JP1483326201_UHD.jpg","dateUrl":"day/202606/22.html","downloadUrl":"https://cn.bing.com/th?id=OHR.Fujisan_JA-JP1483326201_UHD.jpg","title":"富士山","desc":"富士山"},"23":{"date":"2026-06-23","copyright":"キノート・レイン・フォレスト, 米国 ワシントン州","previewUrl":"https://cn.bing.com/th?id=OHR.QuinaultFerns_JA-JP6908853562_UHD.jpg","dateUrl":"day/202606/23.html","downloadUrl":"https://cn.bing.com/th?id=OHR.QuinaultFerns_JA-JP6908853562_UHD.jpg","title":"キノート・レイン・フォレスト, 米国 ワシントン州","desc":"キノート・レイン・フォレスト, 米国 ワシントン州"},"01":{"date":"2026-06-01","copyright":"西タイジナール湖, 中国","previewUrl":"https://cn.bing.com/th?id=OHR.Qinghai_JA-JP8687946851_UHD.jpg","dateUrl":"day/202606/01.html","downloadUrl":"https://cn.bing.com/th?id=OHR.Qinghai_JA-JP8687946851_UHD.jpg","title":"西タイジナール湖, 中国","desc":"西タイジナール湖, 中国"},"24":{"date":"2026-06-24","copyright":"花の蜜を味わう蝶","previewUrl":"https://cn.bing.com/th?id=OHR.BFPollin_JA-JP2026844024_UHD.jpg","dateUrl":"day/202606/24.html","downloadUrl":"https://cn.bing.com/th?id=OHR.BFPollin_JA-JP2026844024_UHD.jpg","title":"花の蜜を味わう蝶","desc":"花の蜜を味わう蝶"},"02":{"date":"2026-06-02","copyright":"みなとみらい 21 地区, 神奈川県 横浜市","previewUrl":"https://cn.bing.com/th?id=OHR.YokohamaPort2026_JA-JP8907488905_UHD.jpg","dateUrl":"day/202606/02.html","downloadUrl":"https://cn.bing.com/th?id=OHR.YokohamaPort2026_JA-JP8907488905_UHD.jpg","title":"みなとみらい 21 地区, 神奈川県 横浜市","desc":"みなとみらい 21 地区, 神奈川県 横浜市"},"25":{"date":"2026-06-25","copyright":"ラベンダー畑, 北海道 中富良野町","previewUrl":"https://cn.bing.com/th?id=OHR.LavenderSeason2026_JA-JP7050134160_UHD.jpg","dateUrl":"day/202606/25.html","downloadUrl":"https://cn.bing.com/th?id=OHR.LavenderSeason2026_JA-JP7050134160_UHD.jpg","title":"ラベンダー畑, 北海道 中富良野町","desc":"ラベンダー畑, 北海道 中富良野町"},"03":{"date":"2026-06-03","copyright":"バルデナス・レアレス自然公園, スペイン","previewUrl":"https://cn.bing.com/th?id=OHR.BardenasReales_JA-JP9112700614_UHD.jpg","dateUrl":"day/202606/03.html","downloadUrl":"https://cn.bing.com/th?id=OHR.BardenasReales_JA-JP9112700614_UHD.jpg","title":"バルデナス・レアレス自然公園, スペイン","desc":"バルデナス・レアレス自然公園, スペイン"},"26":{"date":"2026-06-26","copyright":"テムズ川, イングランド ロンドン","previewUrl":"https://cn.bing.com/th?id=OHR.ThamesSummer_JA-JP5302199333_UHD.jpg","dateUrl":"day/202606/26.html","downloadUrl":"https://cn.bing.com/th?id=OHR.ThamesSummer_JA-JP5302199333_UHD.jpg","title":"テムズ川, イングランド ロンドン","desc":"テムズ川, イングランド ロンドン"},"04":{"date":"2026-06-04","copyright":"ユキコサギ, 米国 フロリダ州","previewUrl":"https://cn.bing.com/th?id=OHR.PreeningEgret_JA-JP9316676875_UHD.jpg","dateUrl":"day/202606/04.html","downloadUrl":"https://cn.bing.com/th?id=OHR.PreeningEgret_JA-JP9316676875_UHD.jpg","title":"ユキコサギ, 米国 フロリダ州","desc":"ユキコサギ, 米国 フロリダ州"},"05":{"date":"2026-06-05","copyright":"サーレク国立公園, スウェーデン","previewUrl":"https://cn.bing.com/th?id=OHR.WedLapland_JA-JP9552121230_UHD.jpg","dateUrl":"day/202606/05.html","downloadUrl":"https://cn.bing.com/th?id=OHR.WedLapland_JA-JP9552121230_UHD.jpg","title":"サーレク国立公園, スウェーデン","desc":"サーレク国立公園, スウェーデン"},"06":{"date":"2026-06-06","copyright":"ナチェズ・トレース・パークウェイのトレイル, 米国 ミシシッピ州","previewUrl":"https://cn.bing.com/th?id=OHR.HikingNatchez_JA-JP9730895087_UHD.jpg","dateUrl":"day/202606/06.html","downloadUrl":"https://cn.bing.com/th?id=OHR.HikingNatchez_JA-JP9730895087_UHD.jpg","title":"ナチェズ・トレース・パークウェイのトレイル, 米国 ミシシッピ州","desc":"ナチェズ・トレース・パークウェイのトレイル, 米国 ミシシッピ州"},"07":{"date":"2026-06-07","copyright":"プラヤ・ダ・ウルサ, ポルトガル","previewUrl":"https://cn.bing.com/th?id=OHR.Limpets_JA-JP0282972005_UHD.jpg","dateUrl":"day/202606/07.html","downloadUrl":"https://cn.bing.com/th?id=OHR.Limpets_JA-JP0282972005_UHD.jpg","title":"プラヤ・ダ・ウルサ, ポルトガル","desc":"プラヤ・ダ・ウルサ, ポルトガル"},"08":{"date":"2026-06-08","copyright":"海中を泳ぐキタユウレイクラゲ","previewUrl":"https://cn.bing.com/th?id=OHR.Cyanea_JA-JP0508555494_UHD.jpg","dateUrl":"day/202606/08.html","downloadUrl":"https://cn.bing.com/th?id=OHR.Cyanea_JA-JP0508555494_UHD.jpg","title":"海中を泳ぐキタユウレイクラゲ","desc":"海中を泳ぐキタユウレイクラゲ"},"09":{"date":"2026-06-09","copyright":"ヴェルナッツァ, イタリア","previewUrl":"https://cn.bing.com/th?id=OHR.CTNPVernazza_JA-JP0736280487_UHD.jpg","dateUrl":"day/202606/09.html","downloadUrl":"https://cn.bing.com/th?id=OHR.CTNPVernazza_JA-JP0736280487_UHD.jpg","title":"ヴェルナッツァ, イタリア","desc":"ヴェルナッツァ, イタリア"},"10":{"date":"2026-06-10","copyright":"フナウサウポットル, アイスランド","previewUrl":"https://cn.bing.com/th?id=OHR.Hnausapollur_JA-JP1632213498_UHD.jpg","dateUrl":"day/202606/10.html","downloadUrl":"https://cn.bing.com/th?id=OHR.Hnausapollur_JA-JP1632213498_UHD.jpg","title":"フナウサウポットル, アイスランド","desc":"フナウサウポットル, アイスランド"},"11":{"date":"2026-06-11","copyright":"蛍の光がきらめく森, 日本","previewUrl":"https://cn.bing.com/th?id=OHR.FireflySeason2026_JA-JP9350920903_UHD.jpg","dateUrl":"day/202606/11.html","downloadUrl":"https://cn.bing.com/th?id=OHR.FireflySeason2026_JA-JP9350920903_UHD.jpg","title":"蛍の光がきらめく森, 日本","desc":"蛍の光がきらめく森, 日本"},"12":{"date":"2026-06-12","copyright":"ヨーロッパハチクイ, スペイン","previewUrl":"https://cn.bing.com/th?id=OHR.SpainBeeEater_JA-JP8800920985_UHD.jpg","dateUrl":"day/202606/12.html","downloadUrl":"https://cn.bing.com/th?id=OHR.SpainBeeEater_JA-JP8800920985_UHD.jpg","title":"ヨーロッパハチクイ, スペイン","desc":"ヨーロッパハチクイ, スペイン"},"13":{"date":"2026-06-13","copyright":"はやぶさ 2 から切り離されたカプセル","previewUrl":"https://cn.bing.com/th?id=OHR.HayabusaDay2026_JA-JP6590656546_UHD.jpg","dateUrl":"day/202606/13.html","downloadUrl":"https://cn.bing.com/th?id=OHR.HayabusaDay2026_JA-JP6590656546_UHD.jpg","title":"はやぶさ 2 から切り離されたカプセル","desc":"はやぶさ 2 から切り離されたカプセル"},"14":{"date":"2026-06-14","copyright":"バッドランズ国立公園, 米国 サウスダコタ州","previewUrl":"https://cn.bing.com/th?id=OHR.BadSunset_JA-JP5960860484_UHD.jpg","dateUrl":"day/202606/14.html","downloadUrl":"https://cn.bing.com/th?id=OHR.BadSunset_JA-JP5960860484_UHD.jpg","title":"バッドランズ国立公園, 米国 サウスダコタ州","desc":"バッドランズ国立公園, 米国 サウスダコタ州"},"15":{"date":"2026-06-15","copyright":"グレート・スモーキー山脈国立公園, 米国 テネシー州","previewUrl":"https://cn.bing.com/th?id=OHR.ParkEstd_JA-JP9205724491_UHD.jpg","dateUrl":"day/202606/15.html","downloadUrl":"https://cn.bing.com/th?id=OHR.ParkEstd_JA-JP9205724491_UHD.jpg","title":"グレート・スモーキー山脈国立公園, 米国 テネシー州","desc":"グレート・スモーキー山脈国立公園, 米国 テネシー州"},"16":{"date":"2026-06-16","copyright":"優雅に泳ぐタイマイ, ケイマン諸島","previewUrl":"https://cn.bing.com/th?id=OHR.SevenMileTurtle_JA-JP9577560353_UHD.jpg","dateUrl":"day/202606/16.html","downloadUrl":"https://cn.bing.com/th?id=OHR.SevenMileTurtle_JA-JP9577560353_UHD.jpg","title":"優雅に泳ぐタイマイ, ケイマン諸島","desc":"優雅に泳ぐタイマイ, ケイマン諸島"},"17":{"date":"2026-06-17","copyright":"トレモラ道路, スイス","previewUrl":"https://cn.bing.com/th?id=OHR.TremolaRoad_JA-JP0031183332_UHD.jpg","dateUrl":"day/202606/17.html","downloadUrl":"https://cn.bing.com/th?id=OHR.TremolaRoad_JA-JP0031183332_UHD.jpg","title":"トレモラ道路, スイス","desc":"トレモラ道路, スイス"},"18":{"date":"2026-06-18","copyright":"サクサイワマン, ペルー","previewUrl":"https://cn.bing.com/th?id=OHR.Saqsaywaman_JA-JP0282514779_UHD.jpg","dateUrl":"day/202606/18.html","downloadUrl":"https://cn.bing.com/th?id=OHR.Saqsaywaman_JA-JP0282514779_UHD.jpg","title":"サクサイワマン, ペルー","desc":"サクサイワマン, ペルー"},"19":{"date":"2026-06-19","copyright":"グラン＝プラス, ベルギー","previewUrl":"https://cn.bing.com/th?id=OHR.GrandPlace_JA-JP0571812680_UHD.jpg","dateUrl":"day/202606/19.html","downloadUrl":"https://cn.bing.com/th?id=OHR.GrandPlace_JA-JP0571812680_UHD.jpg","title":"グラン＝プラス, ベルギー","desc":"グラン＝プラス, ベルギー"},"20":{"date":"2026-06-20","copyright":"アーチ状の氷山, 南極半島西部","previewUrl":"https://cn.bing.com/th?id=OHR.ArchedIceberg_JA-JP0865478817_UHD.jpg","dateUrl":"day/202606/20.html","downloadUrl":"https://cn.bing.com/th?id=OHR.ArchedIceberg_JA-JP0865478817_UHD.jpg","title":"アーチ状の氷山, 南極半島西部","desc":"アーチ状の氷山, 南極半島西部"},"21":{"date":"2026-06-21","copyright":"オウサマペンギンの父親","previewUrl":"https://cn.bing.com/th?id=OHR.EggDad_JA-JP1066785458_UHD.jpg","dateUrl":"day/202606/21.html","downloadUrl":"https://cn.bing.com/th?id=OHR.EggDad_JA-JP1066785458_UHD.jpg","title":"オウサマペンギンの父親","desc":"オウサマペンギンの父親"}}}